{"name":"整数二分","slug":"算法模板/二分模板/整数二分","count":1,"postlist":[{"title":"整数二分","uid":"f463b7e04b9afca016a6c3b848f9e77c","slug":"整数二分","date":"2022-11-01T16:00:00.000Z","updated":"2022-11-01T16:00:00.000Z","comments":true,"path":"api/articles/整数二分.json","keywords":"notes","cover":null,"text":"对于贪心，某些题会出现WA，比方说逐步贪心的时候每次取出最大值除二，会使最小值偏大如洛谷P3853，则需要用二分去搜索答案。 板子如下：bool check(int x) &#123;&#x2F;* ... *&#x2F;&#125; &#x2F;&#x2F; 检查x是否满足某种...","link":"","photos":[],"count_time":{"symbolsCount":"1.2k","symbolsTime":"1 mins."},"categories":[{"name":"算法模板","slug":"算法模板","count":17,"path":"api/categories/算法模板.json"},{"name":"二分模板","slug":"算法模板/二分模板","count":2,"path":"api/categories/算法模板/二分模板.json"},{"name":"整数二分","slug":"算法模板/二分模板/整数二分","count":1,"path":"api/categories/算法模板/二分模板/整数二分.json"}],"tags":[{"name":"算法模板","slug":"算法模板","count":17,"path":"api/tags/算法模板.json"},{"name":"二分模板","slug":"二分模板","count":2,"path":"api/tags/二分模板.json"},{"name":"整数二分","slug":"整数二分","count":1,"path":"api/tags/整数二分.json"}],"author":{"name":"SMTTY","slug":"blog-author","avatar":"/images/url.jpg","link":"/","description":"学习笔记","socials":{"github":"","twitter":"","stackoverflow":"","wechat":"","qq":"","weibo":"","zhihu":"","csdn":"","juejin":"","customs":{}}},"feature":false}]}